{
  "context": {
    "version": "2.0.0",
    "action": "select",
    "domain": "beckn.one:commerce:aviation:1.0",
    "timestamp": "2025-12-01T08:05:00-08:00",
    "message_id": "msg-select-flight-001",
    "transaction_id": "txn-flight-sfo-jfk-001",
    "bap_id": "travel-booking-app.example.com",
    "bap_uri": "https://travel-booking-app.example.com",
    "bpp_id": "delta-airlines-platform.com",
    "bpp_uri": "https://delta-airlines-platform.com",
    "ttl": "PT30S"
  },
  "message": {
    "order": {
      "@context": "https://raw.githubusercontent.com/beckn/protocol-specifications-new/refs/heads/draft/schema/core/v2/context.jsonld",
      "@type": "beckn:Order",
      "beckn:orderStatus": "QUOTE_REQUESTED",
      "beckn:seller": "provider-delta-airlines",
      "beckn:buyer": {
        "@context": "https://raw.githubusercontent.com/beckn/protocol-specifications-new/refs/heads/draft/schema/core/v2/context.jsonld",
        "@type": "beckn:Buyer",
        "beckn:id": "buyer-fide-beckn"
      },
      "beckn:orderItems": [
        {
          "@context": "https://raw.githubusercontent.com/beckn/protocol-specifications-new/refs/heads/draft/schema/core/v2/context.jsonld",
          "@type": "beckn:OrderItem",
          "beckn:lineId": "line-001",
          "beckn:orderedItem": "item-flight-dl145-economy",
          "beckn:quantity": 1
        }
      ],
      "beckn:fulfillment": {
        "@context": "https://raw.githubusercontent.com/beckn/protocol-specifications-new/refs/heads/draft/schema/core/v2/context.jsonld",
        "@type": "beckn:Fulfillment",
        "beckn:id": "fulfillment-dl145-flight",
        "beckn:mode": "FLIGHT"
      }
    }
  }
}

